flask_restful_dbbase/__init__.py
flask_restful_dbbase/_version.py
flask_restful_dbbase/doc_utils.py
flask_restful_dbbase/generator.py
flask_restful_dbbase/validations.py
flask_restful_dbbase/resources/__init__.py
flask_restful_dbbase/resources/collection_model_resource.py
flask_restful_dbbase/resources/dbbase_resource.py
flask_restful_dbbase/resources/meta_resource.py
flask_restful_dbbase/resources/model_resource.py
Flask_RESTful_DBBase-0.4.0.dist-info/LICENSE.txt
Flask_RESTful_DBBase-0.4.0.dist-info/METADATA
Flask_RESTful_DBBase-0.4.0.dist-info/WHEEL
Flask_RESTful_DBBase-0.4.0.dist-info/top_level.txt
Flask_RESTful_DBBase-0.4.0.dist-info/RECORD
