Metadata-Version: 2.1
Name: Flask-RESTful-DBBase
Version: 0.4.0
Summary: A package that extends Flask-RESTful resources to make creating resources for database use easier and faster.
Home-page: https://sidorof.github.io/flask-restful-dbbase/
Author: Donald Smiley
Author-email: dsmiley@sidorof.com
License: MIT
Classifier: Framework :: Flask
Classifier: Environment :: Web Environment
Classifier: Intended Audience :: Developers
Classifier: License :: OSI Approved :: MIT License
Classifier: Topic :: Software Development
Classifier: Programming Language :: Python
Classifier: Programming Language :: Python :: 3.7
Classifier: Programming Language :: Python :: 3.8
Classifier: Programming Language :: Python :: 3.9
Classifier: Programming Language :: Python :: 3.10
Classifier: Operating System :: OS Independent
Classifier: Programming Language :: Python
Classifier: Topic :: Internet :: WWW/HTTP :: Dynamic Content
Classifier: Topic :: Software Development :: Libraries :: Python Modules
Requires-Python: >=3.7
License-File: LICENSE.txt
Requires-Dist: flask
Requires-Dist: Flask-RESTful
Requires-Dist: SQLAlchemy (<1.4)
Requires-Dist: Flask-SQLAlchemy
Requires-Dist: DBBase
Requires-Dist: python-dateutil
Requires-Dist: inflect
Provides-Extra: dev
Requires-Dist: unittest ; extra == 'dev'
Requires-Dist: pytest ; extra == 'dev'
